sharepoint_too/__init__.py
sharepoint_too/session.py
sharepoint_too-0.3.0.dist-info/AUTHORS.md
sharepoint_too-0.3.0.dist-info/LICENSE
sharepoint_too-0.3.0.dist-info/METADATA
sharepoint_too-0.3.0.dist-info/WHEEL
sharepoint_too-0.3.0.dist-info/top_level.txt
sharepoint_too-0.3.0.dist-info/RECORD
