Metadata-Version: 2.1
Name: sharepoint-too
Version: 0.3.0
Summary: This module will handle authentication for your SharePoint Online/O365 site, allowing you to make straightforward HTTP requests from Python. It extends the commonly used Requests module, meaning that returned objects are familliar, easy to work with and well documented.
Author-email: Tim Santor <tsantor@xstudios.com>
Project-URL: Repository, https://github.com/tsantor/sharepoint-too.git
Project-URL: Issues, https://github.com/tsantor/sharepoint-too/issues
Project-URL: Changelog, https://github.com/tsantor/sharepoint-too/blob/master/HISTORY.md
Classifier: Development Status :: 5 - Production/Stable
Classifier: Environment :: Console
Classifier: Intended Audience :: Developers
Classifier: Natural Language :: English
Classifier: Programming Language :: Python :: 3.8
Classifier: Programming Language :: Python :: 3.9
Classifier: Programming Language :: Python :: 3.10
Classifier: Programming Language :: Python :: 3.11
Classifier: Programming Language :: Python :: 3.12
Requires-Python: >=3.8
License-File: LICENSE
License-File: AUTHORS.md
Requires-Dist: requests-ntlm
Requires-Dist: requests
Provides-Extra: dev
